bloghead/__init__.py
bloghead/djot-server.dist.js
bloghead/djot.py
bloghead/djot_ipc.py
bloghead/icons/COPYING-ICONS
bloghead/icons/application-exit.svg
bloghead/icons/audio-x-generic.svg
bloghead/icons/cloud-upload.svg
bloghead/icons/document-edit.svg
bloghead/icons/document-new.svg
bloghead/icons/document-open.svg
bloghead/icons/document-revert.svg
bloghead/icons/document-save-as.svg
bloghead/icons/document-save.svg
bloghead/icons/edit-delete.svg
bloghead/icons/edit-redo.svg
bloghead/icons/edit-undo.svg
bloghead/icons/folder-open.svg
bloghead/icons/folder.svg
bloghead/icons/format-text-bold.svg
bloghead/icons/format-text-italic.svg
bloghead/icons/image-x-generic.svg
bloghead/icons/link.svg
bloghead/icons/upload-media.svg
bloghead/icons/video-x-generic.svg
bloghead/main.py
bloghead/persistence/__init__.py
bloghead/persistence/common.py
bloghead/persistence/models.py
bloghead/persistence/schema.sql
bloghead/resources.py
bloghead/resources.qrc
bloghead-0.1.1.dist-info/METADATA
bloghead-0.1.1.dist-info/WHEEL
bloghead-0.1.1.dist-info/entry_points.txt
bloghead-0.1.1.dist-info/RECORD
