Metadata-Version: 2.1
Name: bloghead
Version: 0.1.1
Summary: 
License: GPL-3.0-only
Author: Nhân
Author-email: hi@imnhan.com
Requires-Python: >=3.9,<3.11
Classifier: License :: OSI Approved :: GNU General Public License v3 (GPLv3)
Classifier: Programming Language :: Python :: 3
Classifier: Programming Language :: Python :: 3.9
Classifier: Programming Language :: Python :: 3.10
Requires-Dist: peewee (>=3.16,<4.0)
Requires-Dist: pyside2 (>=5.15,<6.0)
